latinum_wallet_mcp/__init__.py
latinum_wallet_mcp/base_wallet_mcp.py
latinum_wallet_mcp/server_sse.py
latinum_wallet_mcp/server_stdio.py
latinum_wallet_mcp/solana_wallet_mcp.py
latinum_wallet_mcp/utils.py
latinum_wallet_mcp-0.0.36.dist-info/METADATA
latinum_wallet_mcp-0.0.36.dist-info/WHEEL
latinum_wallet_mcp-0.0.36.dist-info/entry_points.txt
latinum_wallet_mcp-0.0.36.dist-info/top_level.txt
latinum_wallet_mcp-0.0.36.dist-info/RECORD
