Metadata-Version: 2.4
Name: latinum-wallet-mcp
Version: 0.0.36
Summary: Latinum Wallet MCP Server
Requires-Python: >=3.10
Requires-Dist: mcp
Requires-Dist: google-adk
Requires-Dist: solana
Requires-Dist: solders
Requires-Dist: base58
Requires-Dist: python-dotenv
Requires-Dist: resend
Requires-Dist: supabase
Requires-Dist: keyring
Requires-Dist: deprecated
